factoryman/__init__.py
factoryman/fields.py
factory_man-1.2.3.dist-info/LICENSE
factory_man-1.2.3.dist-info/METADATA
factory_man-1.2.3.dist-info/WHEEL
factory_man-1.2.3.dist-info/top_level.txt
factory_man-1.2.3.dist-info/RECORD
