Metadata-Version: 2.1
Name: factory-man
Version: 1.2.3
Summary: Django specific Extensions for Factory Boy
Home-page: https://gitlab.com/eeriksp/factory-man
Author: Eerik Sven Puudist
Author-email: eerik@smartworks.ee
License: UNKNOWN
Platform: UNKNOWN
Classifier: Programming Language :: Python :: 3
Classifier: License :: OSI Approved :: MIT License
Classifier: Operating System :: OS Independent
Requires-Dist: factory-boy
